udatastore/__init__.py
udatastore/_version.py
udatastore/builder.py
udatastore/data_proxy.py
udatastore/document.py
udatastore/fields.py
udatastore/helpers.py
udatastore/instance.py
udatastore/reference.py
udatastore-0.1.7.dist-info/LICENSE
udatastore-0.1.7.dist-info/METADATA
udatastore-0.1.7.dist-info/WHEEL
udatastore-0.1.7.dist-info/top_level.txt
udatastore-0.1.7.dist-info/RECORD
