Metadata-Version: 2.1
Name: udatastore
Version: 0.1.7
Summary: Datastore framework implementation for umongo
Home-page: https://github.com/ml2grow/udatastore
Author: javdrher
Author-email: joachim@ml2grow.com
License: Apache License 2.0
Keywords: udatastore umongo pymongo datastore
Platform: UNKNOWN
Classifier: Development Status :: 3 - Alpha
Classifier: Intended Audience :: Developers
Classifier: License :: OSI Approved :: Apache Software License
Classifier: Natural Language :: English
Classifier: Programming Language :: Python :: 3
Classifier: Programming Language :: Python :: 3.6
Requires-Dist: umongo (<1.3,>=1.2.0)
Requires-Dist: pymongo (<3.8,>=3.7.2)
Requires-Dist: google-cloud-datastore (<1.8,>=1.7.0)
Provides-Extra: test
Requires-Dist: nox ; extra == 'test'
